decoders/__init__.py
decoders/ac97/__init__.py
decoders/ac97/pd.py
decoders/ad5626/__init__.py
decoders/ad5626/pd.py
decoders/ad79x0/__init__.py
decoders/ad79x0/pd.py
decoders/ade77xx/__init__.py
decoders/ade77xx/lists.py
decoders/ade77xx/pd.py
decoders/adf435x/__init__.py
decoders/adf435x/pd.py
decoders/adns5020/__init__.py
decoders/adns5020/pd.py
decoders/adxl345/__init__.py
decoders/adxl345/lists.py
decoders/adxl345/pd.py
decoders/am230x/__init__.py
decoders/am230x/pd.py
decoders/amulet_ascii/__init__.py
decoders/amulet_ascii/lists.py
decoders/amulet_ascii/pd.py
decoders/arm_etmv3/__init__.py
decoders/arm_etmv3/pd.py
decoders/arm_itm/__init__.py
decoders/arm_itm/pd.py
decoders/arm_tpiu/__init__.py
decoders/arm_tpiu/pd.py
decoders/atsha204a/__init__.py
decoders/atsha204a/pd.py
decoders/aud/__init__.py
decoders/aud/pd.py
decoders/avr_isp/__init__.py
decoders/avr_isp/parts.py
decoders/avr_isp/pd.py
decoders/avr_pdi/__init__.py
decoders/avr_pdi/pd.py
decoders/caliper/__init__.py
decoders/caliper/pd.py
decoders/can/__init__.py
decoders/can/pd.py
decoders/cc1101/__init__.py
decoders/cc1101/lists.py
decoders/cc1101/pd.py
decoders/cec/__init__.py
decoders/cec/pd.py
decoders/cec/protocoldata.py
decoders/cfp/__init__.py
decoders/cfp/pd.py
decoders/cjtag/__init__.py
decoders/cjtag/pd.py
decoders/common/__init__.py
decoders/common/plugtrx/__init__.py
decoders/common/plugtrx/mod.py
decoders/common/sdcard/__init__.py
decoders/common/sdcard/mod.py
decoders/common/srdhelper/__init__.py
decoders/common/srdhelper/mod.py
decoders/counter/__init__.py
decoders/counter/pd.py
decoders/dali/__init__.py
decoders/dali/lists.py
decoders/dali/pd.py
decoders/dcf77/__init__.py
decoders/dcf77/pd.py
decoders/dmx512/__init__.py
decoders/dmx512/pd.py
decoders/ds1307/__init__.py
decoders/ds1307/pd.py
decoders/ds2408/__init__.py
decoders/ds2408/pd.py
decoders/ds243x/__init__.py
decoders/ds243x/pd.py
decoders/ds28ea00/__init__.py
decoders/ds28ea00/pd.py
decoders/dsi/__init__.py
decoders/dsi/pd.py
pysigrok_libsigrokdecode-0.0.2.dist-info/entry_points.txt
pysigrok_libsigrokdecode-0.0.2.dist-info/COPYING
pysigrok_libsigrokdecode-0.0.2.dist-info/WHEEL
pysigrok_libsigrokdecode-0.0.2.dist-info/METADATA
pysigrok_libsigrokdecode-0.0.2.dist-info/RECORD
